AcraNetwork/IENA.py
AcraNetwork/MPEGTS.py
AcraNetwork/McastSocket.py
AcraNetwork/NPD.py
AcraNetwork/ParserAligned.py
AcraNetwork/Pcap.py
AcraNetwork/SamDec008.py
AcraNetwork/SimpleEthernet.py
AcraNetwork/__init__.py
AcraNetwork/__version__.py
AcraNetwork/iNET.py
AcraNetwork/iNetX.py
AcraNetwork/nanotime.py
AcraNetwork/ptptime.py
AcraNetwork/IRIG106/__init__.py
AcraNetwork/IRIG106/Chapter10/Chapter10UDP.py
AcraNetwork/IRIG106/Chapter10/FileParser.py
AcraNetwork/IRIG106/Chapter10/__init__.py
AcraNetwork/IRIG106/Chapter11/ARINC429.py
AcraNetwork/IRIG106/Chapter11/Analog.py
AcraNetwork/IRIG106/Chapter11/CAN.py
AcraNetwork/IRIG106/Chapter11/ComputerData.py
AcraNetwork/IRIG106/Chapter11/MILSTD1553.py
AcraNetwork/IRIG106/Chapter11/PCM.py
AcraNetwork/IRIG106/Chapter11/TimeDataFormat.py
AcraNetwork/IRIG106/Chapter11/UART.py
AcraNetwork/IRIG106/Chapter11/Video.py
AcraNetwork/IRIG106/Chapter11/__init__.py
AcraNetwork/IRIG106/Chapter7/Golay.py
AcraNetwork/IRIG106/Chapter7/__init__.py
AcraNetwork/MPEG/ADTS.py
AcraNetwork/MPEG/H264.py
AcraNetwork/MPEG/PES.py
AcraNetwork/MPEG/PMT.py
AcraNetwork/MPEG/STANAG4609.py
AcraNetwork/MPEG/__init__.py
acranetwork-1.2.4.data/scripts/adau_to_ch10.py
acranetwork-1.2.4.data/scripts/ch10_recorder.py
acranetwork-1.2.4.data/scripts/ch10_to_pcap.py
acranetwork-1.2.4.data/scripts/pkg_gen.ini
acranetwork-1.2.4.data/scripts/tx_iena_udp.py
acranetwork-1.2.4.data/scripts/tx_inetx_udp.py
acranetwork-1.2.4.data/scripts/validate_ch10.py
acranetwork-1.2.4.data/scripts/validate_pcap.py
acranetwork-1.2.4.dist-info/licenses/LICENSE
test/__init__.py
test/test_afdx.py
test/test_ch10.py
test/test_ch7.py
test/test_golay.py
test/test_iena.py
test/test_inet.py
test/test_inetx.py
test/test_misc.py
test/test_mpegts.py
test/test_npd.py
test/test_paligned.py
test/test_pcap.py
test/test_ptptime.py
test/test_simpleethernet.py
acranetwork-1.2.4.dist-info/METADATA
acranetwork-1.2.4.dist-info/WHEEL
acranetwork-1.2.4.dist-info/top_level.txt
acranetwork-1.2.4.dist-info/RECORD
