Metadata-Version: 2.4
Name: AcraNetwork
Version: 1.2.4
Summary: Classes and utilities to support Flight Test Instrumentation Ethernet networks
Home-page: https://github.com/diarmuidcwc/AcraNetwork
Author: Diarmuid Collins
Author-email: dcollins@curtisswright.com
License: GNU GPLv3
Keywords: ACRA,iNetX,FTI,IENA
Classifier: Programming Language :: Python
Classifier: Operating System :: OS Independent
Classifier: Development Status :: 3 - Alpha
Classifier: Intended Audience :: Developers
Classifier: Topic :: Software Development :: Libraries :: Python Modules
Requires-Python: >=3.7
License-File: LICENSE
Dynamic: license-file
